{
    "modules": [
        {
            "config": {
                "position": [
                    69,
                    121
                ]
            },
            "name": "New Model Object",
            "value": {
                "actionGroup": {
                    "_default0_list": true,
                    "_default1_show": false,
                    "_default2_new_create": false,
                    "_default3_edit_update": false,
                    "_default4_delete": false,
                    "customActions": [

                    ]
                },
                "name": "Hellobar",
                "objectsettings": {
                    "addDeletedField": true,
                    "addHiddenField": true,
                    "addStarttimeEndtimeFields": true,
                    "aggregateRoot": true,
                    "categorizable": false,
                    "description": "",
                    "mapToTable": "",
                    "parentClass": "",
                    "sorting": true,
                    "type": "Entity",
                    "uid": "107864947772"
                },
                "propertyGroup": {
                    "properties": [
                        {
                            "allowedFileTypes": "",
                            "maxItems": "1",
                            "propertyDescription": "",
                            "propertyIsExcludeField": true,
                            "propertyIsRequired": false,
                            "propertyName": "test",
                            "propertyType": "String",
                            "uid": "1057408675138"
                        }
                    ]
                },
                "relationGroup": {
                    "relations": [

                    ]
                }
            }
        }
    ],
    "properties": {
        "backendModules": [

        ],
        "description": "NITSAN Hellobar",
        "emConf": {
            "category": "plugin",
            "custom_category": "",
            "dependsOn": "",
            "disableLocalization": false,
            "disableVersioning": false,
            "skipGenerateDocumentationTemplate": false,
            "sourceLanguage": "en",
            "state": "alpha",
            "targetVersion": "7.6.0-7.6.99",
            "version": "1.0.0"
        },
        "extensionKey": "nitsan_hellobar",
        "name": "NITSAN hellobar",
        "originalExtensionKey": "nitsan_hellobar",
        "originalVendorName": "Nitsanhellobar",
        "persons": [

        ],
        "plugins": [
            {
                "actions": {
                    "controllerActionCombinations": "",
                    "noncacheableActions": "",
                    "switchableActions": ""
                },
                "key": "nitsanhellobar",
                "name": "Nitsan Hellobar"
            }
        ],
        "vendorName": "Nitsanhellobar"
    },
    "wires": [

    ],
    "log": {
        "last_modified": "2016-04-28 05:06",
        "extension_builder_version": "7.6.0",
        "be_user": "Sanjay Chuahan (1)"
    }
}